Metadata-Version: 1.0
Name: oskarryn-udacity-distributions
Version: 0.2
Summary: Gaussian and Binomial distributions
Home-page: UNKNOWN
Author: Oskar Rynkiewicz
Author-email: UNKNOWN
License: UNKNOWN
Platform: UNKNOWN
